distans/__init__.py
distans/edit.py
distans/lp_space.py
distans/py.typed
distans/stuff.py
distans/utils.py
distans-0.1.6.dist-info/LICENSE
distans-0.1.6.dist-info/METADATA
distans-0.1.6.dist-info/WHEEL
distans-0.1.6.dist-info/RECORD
