Metadata-Version: 2.1
Name: distans
Version: 0.1.6
Summary: Different distances for Python
Home-page: https://github.com/cospectrum/distans
License: Apache-2.0
Author: cospectrum
Author-email: severinalexeyv@gmail.com
Requires-Python: >=3.8,<4.0
Classifier: License :: OSI Approved :: Apache Software License
Classifier: Programming Language :: Python :: 3
Classifier: Programming Language :: Python :: 3.8
Classifier: Programming Language :: Python :: 3.9
Classifier: Programming Language :: Python :: 3.10
Classifier: Programming Language :: Python :: 3.11
Project-URL: Repository, https://github.com/cospectrum/distans
